process_improvement/__init__.py
process_improvement/comparison_charts.py
process_improvement/limit_charts.py
process_improvement/network_analysis.py
process_improvement/process_capability.py
process_improvement/xmr_charts.py
process_improvement-1.1.4.dist-info/licenses/LICENSE.txt
process_improvement-1.1.4.dist-info/METADATA
process_improvement-1.1.4.dist-info/WHEEL
process_improvement-1.1.4.dist-info/top_level.txt
process_improvement-1.1.4.dist-info/RECORD
