Metadata-Version: 2.4
Name: process_improvement
Version: 1.1.4
Summary: A Python package for undersanding variation in business and manufacturing processes using process behavior charts.
Author-email: Jim Lehner <James.Lehner@gmail.com>
Project-URL: Homepage, https://github.com/jimlehner/py-process-improvement
Project-URL: Repository, https://github.com/jimlehner/py-process-improvement
Requires-Python: >=3.6
License-File: LICENSE.txt
Requires-Dist: numpy
Requires-Dist: pandas
Requires-Dist: matplotlib
Requires-Dist: seaborn
Dynamic: license-file
